AUTHORS.rst
CONTRIBUTING.rst
HISTORY.rst
LICENSE
MANIFEST.in
README.rst
setup.cfg
setup.py
django_sheets.egg-info/PKG-INFO
django_sheets.egg-info/SOURCES.txt
django_sheets.egg-info/dependency_links.txt
django_sheets.egg-info/not-zip-safe
django_sheets.egg-info/requires.txt
django_sheets.egg-info/top_level.txt
sheets/__init__.py
sheets/models.py
sheets/templatetags/__init__.py
sheets/templatetags/sheets.py