Metadata-Version: 1.1
Name: django-sheets
Version: 0.1.2
Summary: Use Google Sheets as context variables in Django templates
Home-page: https://github.com/georgewhewell/django-sheets
Author: George Whewell
Author-email: georgerw@gmail.com
License: BSD
Keywords: django-sheets
Platform: UNKNOWN
Classifier: Development Status :: 4 - Beta
Classifier: Framework :: Django
Classifier: Intended Audience :: Developers
Classifier: License :: OSI Approved :: BSD License
Classifier: Natural Language :: English
Classifier: Programming Language :: Python :: 2
Classifier: Programming Language :: Python :: 2.7
Classifier: Programming Language :: Python :: 3
Classifier: Programming Language :: Python :: 3.3
Classifier: Programming Language :: Python :: 3.4
